{
  "/_not-found/page": "app/_not-found/page.js",
  "/admin/programs/[programKey]/clone/submit/route": "app/admin/programs/[programKey]/clone/submit/route.js",
  "/admin/programs/[programKey]/details/save/route": "app/admin/programs/[programKey]/details/save/route.js",
  "/admin/programs/[programKey]/requirements/save/route": "app/admin/programs/[programKey]/requirements/save/route.js",
  "/admin/programs/[programKey]/toggle/route": "app/admin/programs/[programKey]/toggle/route.js",
  "/admin/programs/create/route": "app/admin/programs/create/route.js",
  "/admin/readiness/[programKey]/save/route": "app/admin/readiness/[programKey]/save/route.js",
  "/cases/[id]/notes/create/route": "app/cases/[id]/notes/create/route.js",
  "/cases/[id]/program/set/route": "app/cases/[id]/program/set/route.js",
  "/cases/[id]/tasks/create/route": "app/cases/[id]/tasks/create/route.js",
  "/cases/[id]/verifications/create/route": "app/cases/[id]/verifications/create/route.js",
  "/cases/new/create/route": "app/cases/new/create/route.js",
  "/documents/[id]/download/route": "app/documents/[id]/download/route.js",
  "/notes/[id]/addendum/route": "app/notes/[id]/addendum/route.js",
  "/notes/[id]/sign/route": "app/notes/[id]/sign/route.js",
  "/tasks/[id]/complete/route": "app/tasks/[id]/complete/route.js",
  "/verifications/[id]/complete-from-evidence/route": "app/verifications/[id]/complete-from-evidence/route.js",
  "/verifications/[id]/evidence/route": "app/verifications/[id]/evidence/route.js",
  "/verifications/[id]/set/route": "app/verifications/[id]/set/route.js",
  "/admin/programs/[programKey]/clone/page": "app/admin/programs/[programKey]/clone/page.js",
  "/admin/programs/[programKey]/page": "app/admin/programs/[programKey]/page.js",
  "/admin/programs/page": "app/admin/programs/page.js",
  "/admin/readiness/[programKey]/page": "app/admin/readiness/[programKey]/page.js",
  "/admin/readiness/page": "app/admin/readiness/page.js",
  "/cases/[id]/page": "app/cases/[id]/page.js",
  "/cases/new/page": "app/cases/new/page.js",
  "/cases/page": "app/cases/page.js",
  "/page": "app/page.js",
  "/tasks/page": "app/tasks/page.js"
}